binary_morphology_cpp.cp36-win_amd64.pyd
cylindrical_binary_morphology_cpp.cp36-win_amd64.pyd
greyscale_morphology_cpp.cp36-win_amd64.pyd
morphology_cuda.cp36-win_amd64.pyd
nnMorpho/__init__.py
nnMorpho/binary_operations.py
nnMorpho/checks.py
nnMorpho/cylindric_binary_operations.py
nnMorpho/functions.py
nnMorpho/modules.py
nnMorpho/operations.py
nnMorpho/parameters.py
nnMorpho/utils.py
nnMorpho-2.2.1.dist-info/LICENSE
nnMorpho-2.2.1.dist-info/METADATA
nnMorpho-2.2.1.dist-info/WHEEL
nnMorpho-2.2.1.dist-info/top_level.txt
nnMorpho-2.2.1.dist-info/RECORD
