Metadata-Version: 2.1
Name: nnMorpho
Version: 2.2.1
Summary: A library for GPU-accelerated and Machine-Learning adapted Mathematical Morphology
Home-page: https://github.com/Manza12/nnMorpho
Author: Gonzalo Romero-García
Author-email: tritery@hotmail.com
License: MIT
Download-URL: https://github.com/Manza12/nnMorpho/archive/v_0.1.tar.gz
Keywords: Mathematical Morphology,PyTorch,GPU,CUDA
Platform: UNKNOWN
Classifier: Development Status :: 3 - Alpha
Classifier: Intended Audience :: Developers
Classifier: Topic :: Software Development :: Build Tools
Classifier: License :: OSI Approved :: MIT License
Classifier: Programming Language :: Python :: 3
Classifier: Programming Language :: Python :: 3.4
Classifier: Programming Language :: Python :: 3.5
Classifier: Programming Language :: Python :: 3.6
License-File: LICENSE
Requires-Dist: numpy
Requires-Dist: torch
